habapp_rules/__init__.py
habapp_rules/actors/__init__.py
habapp_rules/actors/energy_save_switch.py
habapp_rules/actors/heating.py
habapp_rules/actors/irrigation.py
habapp_rules/actors/light.py
habapp_rules/actors/light_bathroom.py
habapp_rules/actors/light_hcl.py
habapp_rules/actors/shading.py
habapp_rules/actors/state_observer.py
habapp_rules/actors/ventilation.py
habapp_rules/actors/config/__init__.py
habapp_rules/actors/config/energy_save_switch.py
habapp_rules/actors/config/heating.py
habapp_rules/actors/config/irrigation.py
habapp_rules/actors/config/light.py
habapp_rules/actors/config/light_bathroom.py
habapp_rules/actors/config/light_hcl.py
habapp_rules/actors/config/shading.py
habapp_rules/actors/config/ventilation.py
habapp_rules/bridge/__init__.py
habapp_rules/bridge/knx_mqtt.py
habapp_rules/bridge/config/__init__.py
habapp_rules/bridge/config/knx_mqtt.py
habapp_rules/common/__init__.py
habapp_rules/common/filter.py
habapp_rules/common/hysteresis.py
habapp_rules/common/logic.py
habapp_rules/common/config/__init__.py
habapp_rules/common/config/filter.py
habapp_rules/common/config/logic.py
habapp_rules/core/__init__.py
habapp_rules/core/exceptions.py
habapp_rules/core/helper.py
habapp_rules/core/logger.py
habapp_rules/core/pydantic_base.py
habapp_rules/core/state_machine_rule.py
habapp_rules/core/timeout_list.py
habapp_rules/core/type_of_day.py
habapp_rules/core/version.py
habapp_rules/energy/__init__.py
habapp_rules/energy/donut_chart.py
habapp_rules/energy/helper.py
habapp_rules/energy/monthly_report.py
habapp_rules/energy/monthly_report_template.html
habapp_rules/energy/virtual_energy_meter.py
habapp_rules/energy/config/__init__.py
habapp_rules/energy/config/monthly_report.py
habapp_rules/energy/config/virtual_energy_meter.py
habapp_rules/media/__init__.py
habapp_rules/media/sonos.py
habapp_rules/media/config/__init__.py
habapp_rules/media/config/sonos.py
habapp_rules/network/__init__.py
habapp_rules/network/wol.py
habapp_rules/network/config/__init__.py
habapp_rules-9.0.0.dist-info/METADATA
habapp_rules-9.0.0.dist-info/WHEEL
habapp_rules-9.0.0.dist-info/licenses/LICENCE
habapp_rules-9.0.0.dist-info/RECORD
