Metadata-Version: 2.4
Name: habapp_rules
Version: 9.0.0
Summary: Basic rules for HABApp
Author: Seuling N.
License-Expression: Apache-2.0
License-File: LICENCE
Requires-Python: >=3.10
Requires-Dist: habapp==25.7.0
Requires-Dist: matplotlib~=3.10.0
Requires-Dist: multi-notifier~=0.5.0
Requires-Dist: pydantic-extra-types~=2.10.2
Requires-Dist: transitions==0.9.1
Requires-Dist: typing-extensions~=4.14.0
Requires-Dist: wakeonlan~=3.1.0
